Workbook

Sheet Резюме
B2: P&L AMAZON EU — ИТОГОВЫЙ ОТЧЁТ
B3: Сравнение двух производителей · 5 товаров · горизонт 12 месяцев (год 1, фаза запуска). Все суммы в €.
B5: ВЫВОД
B6: МЕРИВУД выгоднее ERA примерно на €3 344/год за счёт более низкой совокупной себестоимости (при идентичных объёмах, ценах и расходах на рекламу). Оба сценария по итогам 1-го года убыточны — это заложенная в план фаза агрессивного запуска (высокий PPC, наработка органики и LTV). Драйверы прибыли — Pet-пробиотик и Ретинол; самый убыточный товар на старте — Иноситол.
C11: Чистый рез-т Y1 · МЕРИВУД | D11: Чистый рез-т Y1 · ERA | E11: Преимущество МЕРИВУД
C12: ='P&L Меривуд'!O30 -> -6100.141 | D12: ='P&L ERA'!O30 -> -9444.166 | E12: ='P&L Меривуд'!O30-'P&L ERA'!O30 -> 3344.025
C13: после всех расходов | D13: после всех расходов | E13: за счёт себестоимости
B15: СТАТЬЯ P&L (год) | C15: МЕРИВУД | D15: ERA | E15: Разница
B16: Валовая выручка | C16: ='P&L Меривуд'!O6 -> 511267.5 | D16: ='P&L ERA'!O6 -> 511267.5 | E16: =C16-D16 -> 0
B17: Возвраты (1%) | C17: ='P&L Меривуд'!O7 -> -5112.675 | D17: ='P&L ERA'!O7 -> -5112.675 | E17: =C17-D17 -> 0
B18: Чистая выручка | C18: ='P&L Меривуд'!O8 -> 506154.83 | D18: ='P&L ERA'!O8 -> 506154.83 | E18: =C18-D18 -> 0
B19: Себестоимость (COGS) | C19: ='P&L Меривуд'!O10 -> -85136.21 | D19: ='P&L ERA'!O10 -> -88480.235 | E19: =C19-D19 -> 3344.025
B20: ВАЛОВАЯ ПРИБЫЛЬ | C20: ='P&L Меривуд'!O11 -> 421018.61 | D20: ='P&L ERA'!O11 -> 417674.59 | E20: =C20-D20 -> 3344.025
B21: Комиссия Amazon (15%) | C21: ='P&L Меривуд'!O15 -> -76690.125 | D21: ='P&L ERA'!O15 -> -76690.125 | E21: =C21-D21 -> 0
B22: FBA фулфилмент | C22: ='P&L Меривуд'!O16 -> -65493.3 | D22: ='P&L ERA'!O16 -> -65493.3 | E22: =C22-D22 -> 0
B23: Входящая логистика | C23: ='P&L Меривуд'!O17 -> -5457.775 | D23: ='P&L ERA'!O17 -> -5457.775 | E23: =C23-D23 -> 0
B24: Преп и маркировка | C24: ='P&L Меривуд'!O18 -> -8732.44 | D24: ='P&L ERA'!O18 -> -8732.44 | E24: =C24-D24 -> 0
B25: Хранение | C25: ='P&L Меривуд'!O19 -> -3274.665 | D25: ='P&L ERA'!O19 -> -3274.665 | E25: =C25-D25 -> 0
B26: Обработка возвратов | C26: ='P&L Меривуд'!O20 -> -218.311 | D26: ='P&L ERA'!O20 -> -218.311 | E26: =C26-D26 -> 0
B27: Купоны / промо | C27: ='P&L Меривуд'!O21 -> -14027.14 | D27: ='P&L ERA'!O21 -> -14027.14 | E27: =C27-D27 -> 0
B28: Реклама PPC | C28: ='P&L Меривуд'!O22 -> -219125 | D28: ='P&L ERA'!O22 -> -219125 | E28: =C28-D28 -> 0
B29: МАРЖИНАЛЬНАЯ ПРИБЫЛЬ | C29: ='P&L Меривуд'!O24 -> 27999.859 | D29: ='P&L ERA'!O24 -> 24655.834 | E29: =C29-D29 -> 3344.025
B30: Постоянные расходы | C30: ='P&L Меривуд'!O27 -> -30000 | D30: ='P&L ERA'!O27 -> -30000 | E30: =C30-D30 -> 0
B31: EBITDA | C31: ='P&L Меривуд'!O28 -> -2000.141 | D31: ='P&L ERA'!O28 -> -5344.166 | E31: =C31-D31 -> 3344.025
B32: Разовые расходы (старт) | C32: ='P&L Меривуд'!O29 -> -4100 | D32: ='P&L ERA'!O29 -> -4100 | E32: =C32-D32 -> 0
B33: ЧИСТАЯ ПРИБЫЛЬ Y1 | C33: ='P&L Меривуд'!O30 -> -6100.141 | D33: ='P&L ERA'!O30 -> -9444.166 | E33: =C33-D33 -> 3344.025
B35: КЛЮЧЕВЫЕ ВЫВОДЫ
B36: 1. Разница только в себестоимости: у ERA COGS выше на ≈€3 344/год, поэтому МЕРИВУД даёт лучший итог.
B37: 2. Убыток 1-го года — плановый: основная причина — агрессивный PPC (TACoS ≈43% от выручки на старте).
B38: 3. Прибыльные товары (после PPC): Pet-пробиотик и Ретинол. Убыточные на старте: Иноситол, Магний.
B39: 4. По товарам разница между заводами невелика — выбор стоит делать и по неценовым факторам (MOQ, сроки, сырьё).
B40: 5. МЕРИВУД: MOQ 5 000 шт и 100% предоплата → выше стартовые вложения и риск стока; ERA: MOQ 1 000 и 60% предоплата → гибче на старте.
B42: ⚠ ОГОВОРКА ПРО НДС (важно для интерпретации)
B43: Модель следует логике исходных файлов: выручка взята «как есть» (с НДС, цена листинга), исходящий НДС с продаж не вычитается. Себестоимость — без НДС (intra-EU B2B, reverse charge). Это завышает прибыль обоих сценариев. Если вычесть исходящий НДС DE (19%) с валовой выручки (≈€511k), это ≈ −€97k к результату — оба сценария уходят в глубокий минус. Точную сумму НДС к уплате определяет схема регистрации (OSS/локальная) и доля рынков; ставку можно поменять в ячейке «Допущения!C14».
B49: Источники и метод
B50: Объёмы, цены, PPC и купоны — из файла Amazon_PPC_экономика (план запуска, 5 товаров, помесячно). Себестоимость по заводам — из Юнит_экономика…/Фин_модель (тариф 5 000 шт, без НДС). Комиссия Amazon 15%, FBA €3,0/ед, возвраты 1%, логистика+преп+хранение ≈€0,80/ед, постоянные €2 500/мес, старт €4 100. Все параметры редактируются на листе «Допущения» — P&L и резюме пересчитаются автоматически.

Sheet P&L Меривуд
B2: P&L · Меривуд (€, 12 месяцев)
B3: Статья P&L | C3: Янв | D3: Фев | E3: Мар | F3: Апр | G3: Май | H3: Июн | I3: Июл | J3: Авг | K3: Сен | L3: Окт | M3: Ноя | N3: Дек | O3: ГОД
B4: Объём продаж, ед | C4: =SUM(Допущения!C$25:C$29) -> 129.1 | D4: =SUM(Допущения!D$25:D$29) -> 286.5 | E4: =SUM(Допущения!E$25:E$29) -> 512.8 | F4: =SUM(Допущения!F$25:F$29) -> 779.1 | G4: =SUM(Допущения!G$25:G$29) -> 1075.5 | H4: =SUM(Допущения!H$25:H$29) -> 1424.4 | I4: =SUM(Допущения!I$25:I$29) -> 1742.3 | J4: =SUM(Допущения!J$25:J$29) -> 2228.5 | ... N4: =SUM(Допущения!N$25:N$29) -> 4118.4 | O4: =SUM(C4:N4) -> 21831.1
B6: Валовая выручка | C6: =SUMPRODUCT(Допущения!C$25:C$29,Допущения!$C$18:$C$22) -> 3043.2 | D6: =SUMPRODUCT(Допущения!D$25:D$29,Допущения!$C$18:$C$22) -> 6730.2 | E6: =SUMPRODUCT(Допущения!E$25:E$29,Допущения!$C$18:$C$22) -> 12021.9 | F6: =SUMPRODUCT(Допущения!F$25:F$29,Допущения!$C$18:$C$22) -> 18182.7 | G6: =SUMPRODUCT(Допущения!G$25:G$29,Допущения!$C$18:$C$22) -> 25101 | H6: =SUMPRODUCT(Допущения!H$25:H$29,Допущения!$C$18:$C$22) -> 33242.1 | I6: =SUMPRODUCT(Допущения!I$25:I$29,Допущения!$C$18:$C$22) -> 40730.1 | J6: =SUMPRODUCT(Допущения!J$25:J$29,Допущения!$C$18:$C$22) -> 52143.6 | ... N6: =SUMPRODUCT(Допущения!N$25:N$29,Допущения!$C$18:$C$22) -> 96573.6 | O6: =SUM(C6:N6) -> 511267.5
B7: Возвраты (% от выручки) | C7: =-C6*Допущения!$C$11 -> -30.432 | D7: =-D6*Допущения!$C$11 -> -67.302 | E7: =-E6*Допущения!$C$11 -> -120.219 | F7: =-F6*Допущения!$C$11 -> -181.827 | G7: =-G6*Допущения!$C$11 -> -251.01 | H7: =-H6*Допущения!$C$11 -> -332.421 | I7: =-I6*Допущения!$C$11 -> -407.301 | J7: =-J6*Допущения!$C$11 -> -521.436 | ... N7: =-N6*Допущения!$C$11 -> -965.736 | O7: =SUM(C7:N7) -> -5112.675
B8: Чистая выручка | C8: =C6+C7 -> 3012.768 | D8: =D6+D7 -> 6662.898 | E8: =E6+E7 -> 11901.681 | F8: =F6+F7 -> 18000.873 | G8: =G6+G7 -> 24849.99 | H8: =H6+H7 -> 32909.679 | I8: =I6+I7 -> 40322.799 | J8: =J6+J7 -> 51622.164 | ... N8: =N6+N7 -> 95607.864 | O8: =SUM(C8:N8) -> 506154.83
B10: Себестоимость товара (COGS) | C10: =-SUMPRODUCT(Допущения!C$25:C$29,Допущения!$E$18:$E$22) -> -536.493 | D10: =-SUMPRODUCT(Допущения!D$25:D$29,Допущения!$E$18:$E$22) -> -1156.193 | E10: =-SUMPRODUCT(Допущения!E$25:E$29,Допущения!$E$18:$E$22) -> -2036.393 | F10: =-SUMPRODUCT(Допущения!F$25:F$29,Допущения!$E$18:$E$22) -> -3028.986 | G10: =-SUMPRODUCT(Допущения!G$25:G$29,Допущения!$E$18:$E$22) -> -4166.055 | H10: =-SUMPRODUCT(Допущения!H$25:H$29,Допущения!$E$18:$E$22) -> -5501.627 | I10: =-SUMPRODUCT(Допущения!I$25:I$29,Допущения!$E$18:$E$22) -> -6757.836 | J10: =-SUMPRODUCT(Допущения!J$25:J$29,Допущения!$E$18:$E$22) -> -8659.363 | ... N10: =-SUMPRODUCT(Допущения!N$25:N$29,Допущения!$E$18:$E$22) -> -16075.224 | O10: =SUM(C10:N10) -> -85136.21
B11: ВАЛОВАЯ ПРИБЫЛЬ | C11: =C8+C10 -> 2476.275 | D11: =D8+D10 -> 5506.705 | E11: =E8+E10 -> 9865.288 | F11: =F8+F10 -> 14971.887 | G11: =G8+G10 -> 20683.935 | H11: =H8+H10 -> 27408.052 | I11: =I8+I10 -> 33564.963 | J11: =J8+J10 -> 42962.801 | ... N11: =N8+N10 -> 79532.64 | O11: =SUM(C11:N11) -> 421018.61
B12: % валовой прибыли | C12: =IF(C6=0,0,C11/C6) -> 0.81370761 | D12: =IF(D6=0,0,D11/D6) -> 0.81820823 | E12: =IF(E6=0,0,E11/E6) -> 0.82060972 | F12: =IF(F6=0,0,F11/F6) -> 0.82341385 | G12: =IF(G6=0,0,G11/G6) -> 0.82402833 | H12: =IF(H6=0,0,H11/H6) -> 0.82449821 | I12: =IF(I6=0,0,I11/I6) -> 0.82408251 | J12: =IF(J6=0,0,J11/J6) -> 0.82393239 | ... O12: =IF(O6=0,0,O11/O6) -> 0.82348011
B15: Комиссия Amazon (15%) | C15: =-C6*Допущения!$C$6 -> -456.48 | D15: =-D6*Допущения!$C$6 -> -1009.53 | E15: =-E6*Допущения!$C$6 -> -1803.285 | F15: =-F6*Допущения!$C$6 -> -2727.405 | G15: =-G6*Допущения!$C$6 -> -3765.15 | H15: =-H6*Допущения!$C$6 -> -4986.315 | I15: =-I6*Допущения!$C$6 -> -6109.515 | J15: =-J6*Допущения!$C$6 -> -7821.54 | ... N15: =-N6*Допущения!$C$6 -> -14486.04 | O15: =SUM(C15:N15) -> -76690.125
B16: FBA фулфилмент | C16: =-SUMPRODUCT(Допущения!C$25:C$29,Допущения!$D$18:$D$22) -> -387.3 | D16: =-SUMPRODUCT(Допущения!D$25:D$29,Допущения!$D$18:$D$22) -> -859.5 | E16: =-SUMPRODUCT(Допущения!E$25:E$29,Допущения!$D$18:$D$22) -> -1538.4 | F16: =-SUMPRODUCT(Допущения!F$25:F$29,Допущения!$D$18:$D$22) -> -2337.3 | G16: =-SUMPRODUCT(Допущения!G$25:G$29,Допущения!$D$18:$D$22) -> -3226.5 | H16: =-SUMPRODUCT(Допущения!H$25:H$29,Допущения!$D$18:$D$22) -> -4273.2 | I16: =-SUMPRODUCT(Допущения!I$25:I$29,Допущения!$D$18:$D$22) -> -5226.9 | J16: =-SUMPRODUCT(Допущения!J$25:J$29,Допущения!$D$18:$D$22) -> -6685.5 | ... N16: =-SUMPRODUCT(Допущения!N$25:N$29,Допущения!$D$18:$D$22) -> -12355.2 | O16: =SUM(C16:N16) -> -65493.3
B17: Входящая логистика (завод→FBA) | C17: =-SUM(Допущения!C$25:C$29)*Допущения!$C$8 -> -32.275 | D17: =-SUM(Допущения!D$25:D$29)*Допущения!$C$8 -> -71.625 | E17: =-SUM(Допущения!E$25:E$29)*Допущения!$C$8 -> -128.2 | F17: =-SUM(Допущения!F$25:F$29)*Допущения!$C$8 -> -194.775 | G17: =-SUM(Допущения!G$25:G$29)*Допущения!$C$8 -> -268.875 | H17: =-SUM(Допущения!H$25:H$29)*Допущения!$C$8 -> -356.1 | I17: =-SUM(Допущения!I$25:I$29)*Допущения!$C$8 -> -435.575 | J17: =-SUM(Допущения!J$25:J$29)*Допущения!$C$8 -> -557.125 | ... N17: =-SUM(Допущения!N$25:N$29)*Допущения!$C$8 -> -1029.6 | O17: =SUM(C17:N17) -> -5457.775
B18: Преп и маркировка | C18: =-SUM(Допущения!C$25:C$29)*Допущения!$C$9 -> -51.64 | D18: =-SUM(Допущения!D$25:D$29)*Допущения!$C$9 -> -114.6 | E18: =-SUM(Допущения!E$25:E$29)*Допущения!$C$9 -> -205.12 | F18: =-SUM(Допущения!F$25:F$29)*Допущения!$C$9 -> -311.64 | G18: =-SUM(Допущения!G$25:G$29)*Допущения!$C$9 -> -430.2 | H18: =-SUM(Допущения!H$25:H$29)*Допущения!$C$9 -> -569.76 | I18: =-SUM(Допущения!I$25:I$29)*Допущения!$C$9 -> -696.92 | J18: =-SUM(Допущения!J$25:J$29)*Допущения!$C$9 -> -891.4 | ... N18: =-SUM(Допущения!N$25:N$29)*Допущения!$C$9 -> -1647.36 | O18: =SUM(C18:N18) -> -8732.44
B19: Хранение Amazon | C19: =-SUM(Допущения!C$25:C$29)*Допущения!$C$10 -> -19.365 | D19: =-SUM(Допущения!D$25:D$29)*Допущения!$C$10 -> -42.975 | E19: =-SUM(Допущения!E$25:E$29)*Допущения!$C$10 -> -76.92 | F19: =-SUM(Допущения!F$25:F$29)*Допущения!$C$10 -> -116.865 | G19: =-SUM(Допущения!G$25:G$29)*Допущения!$C$10 -> -161.325 | H19: =-SUM(Допущения!H$25:H$29)*Допущения!$C$10 -> -213.66 | I19: =-SUM(Допущения!I$25:I$29)*Допущения!$C$10 -> -261.345 | J19: =-SUM(Допущения!J$25:J$29)*Допущения!$C$10 -> -334.275 | ... N19: =-SUM(Допущения!N$25:N$29)*Допущения!$C$10 -> -617.76 | O19: =SUM(C19:N19) -> -3274.665
B20: Обработка возвратов | C20: =-SUM(Допущения!C$25:C$29)*Допущения!$C$11*Допущения!$C$12 -> -1.291 | D20: =-SUM(Допущения!D$25:D$29)*Допущения!$C$11*Допущения!$C$12 -> -2.865 | E20: =-SUM(Допущения!E$25:E$29)*Допущения!$C$11*Допущения!$C$12 -> -5.128 | F20: =-SUM(Допущения!F$25:F$29)*Допущения!$C$11*Допущения!$C$12 -> -7.791 | G20: =-SUM(Допущения!G$25:G$29)*Допущения!$C$11*Допущения!$C$12 -> -10.755 | H20: =-SUM(Допущения!H$25:H$29)*Допущения!$C$11*Допущения!$C$12 -> -14.244 | I20: =-SUM(Допущения!I$25:I$29)*Допущения!$C$11*Допущения!$C$12 -> -17.423 | J20: =-SUM(Допущения!J$25:J$29)*Допущения!$C$11*Допущения!$C$12 -> -22.285 | ... N20: =-SUM(Допущения!N$25:N$29)*Допущения!$C$11*Допущения!$C$12 -> -41.184 | O20: =SUM(C20:N20) -> -218.311
B21: Купоны / промо | C21: =-SUM(Допущения!C$41:C$45) -> -75.9 | D21: =-SUM(Допущения!D$41:D$45) -> -183.61 | E21: =-SUM(Допущения!E$41:E$45) -> -335.96 | F21: =-SUM(Допущения!F$41:F$45) -> -532.96 | G21: =-SUM(Допущения!G$41:G$45) -> -805.63 | H21: =-SUM(Допущения!H$41:H$45) -> -1025.15 | I21: =-SUM(Допущения!I$41:I$45) -> -1209.23 | J21: =-SUM(Допущения!J$41:J$45) -> -1492.22 | ... N21: =-SUM(Допущения!N$41:N$45) -> -2416.74 | O21: =SUM(C21:N21) -> -14027.14
B22: Реклама PPC | C22: =-SUM(Допущения!C$33:C$37) -> -6363 | D22: =-SUM(Допущения!D$33:D$37) -> -7560 | E22: =-SUM(Допущения!E$33:E$37) -> -9602 | F22: =-SUM(Допущения!F$33:F$37) -> -11690 | G22: =-SUM(Допущения!G$33:G$37) -> -13763 | H22: =-SUM(Допущения!H$33:H$37) -> -16113 | I22: =-SUM(Допущения!I$33:I$37) -> -18637 | J22: =-SUM(Допущения!J$33:J$37) -> -21260 | ... N22: =-SUM(Допущения!N$33:N$37) -> -33494 | O22: =SUM(C22:N22) -> -219125
B24: МАРЖИНАЛЬНАЯ ПРИБЫЛЬ | C24: =C8+C10+C15+C16+C17+C18+C19+C20+C21+C22 -> -4910.976 | D24: =D8+D10+D15+D16+D17+D18+D19+D20+D21+D22 -> -4338 | E24: =E8+E10+E15+E16+E17+E18+E19+E20+E21+E22 -> -3829.725 | F24: =F8+F10+F15+F16+F17+F18+F19+F20+F21+F22 -> -2946.849 | G24: =G8+G10+G15+G16+G17+G18+G19+G20+G21+G22 -> -1747.5 | H24: =H8+H10+H15+H16+H17+H18+H19+H20+H21+H22 -> -143.377 | I24: =I8+I10+I15+I16+I17+I18+I19+I20+I21+I22 -> 971.055 | J24: =J8+J10+J15+J16+J17+J18+J19+J20+J21+J22 -> 3898.456 | ... N24: =N8+N10+N15+N16+N17+N18+N19+N20+N21+N22 -> 13444.756 | O24: =SUM(C24:N24) -> 27999.859
B25: % маржи (от выручки) | C25: =IF(C6=0,0,C24/C6) -> -1.6137539 | D25: =IF(D6=0,0,D24/D6) -> -0.64455737 | E25: =IF(E6=0,0,E24/E6) -> -0.31856237 | F25: =IF(F6=0,0,F24/F6) -> -0.16206883 | G25: =IF(G6=0,0,G24/G6) -> -0.06961874 | H25: =IF(H6=0,0,H24/H6) -> -0.004313115 | I25: =IF(I6=0,0,I24/I6) -> 0.023841213 | J25: =IF(J6=0,0,J24/J6) -> 0.074763844 | ... O25: =IF(O6=0,0,O24/O6) -> 0.054765576
B27: Постоянные расходы (опер.) | C27: =-Допущения!$C$13 -> -2500 | D27: =-Допущения!$C$13 -> -2500 | E27: =-Допущения!$C$13 -> -2500 | F27: =-Допущения!$C$13 -> -2500 | G27: =-Допущения!$C$13 -> -2500 | H27: =-Допущения!$C$13 -> -2500 | I27: =-Допущения!$C$13 -> -2500 | J27: =-Допущения!$C$13 -> -2500 | ... N27: =-Допущения!$C$13 -> -2500 | O27: =SUM(C27:N27) -> -30000
B28: EBITDA | C28: =C24+C27 -> -7410.976 | D28: =D24+D27 -> -6838 | E28: =E24+E27 -> -6329.725 | F28: =F24+F27 -> -5446.849 | G28: =G24+G27 -> -4247.5 | H28: =H24+H27 -> -2643.377 | I28: =I24+I27 -> -1528.945 | J28: =J24+J27 -> 1398.456 | ... N28: =N24+N27 -> 10944.756 | O28: =SUM(C28:N28) -> -2000.141
B29: Разовые расходы (старт) | C29: =-Допущения!$C$15 -> -4100 | D29: 0 | E29: 0 | F29: 0 | G29: 0 | H29: 0 | I29: 0 | J29: 0 | K29: 0 | L29: 0 | M29: 0 | N29: 0 | O29: =SUM(C29:N29) -> -4100
B30: ЧИСТАЯ ПРИБЫЛЬ | C30: =C28+C29 -> -11510.976 | D30: =D28+D29 -> -6838 | E30: =E28+E29 -> -6329.725 | F30: =F28+F29 -> -5446.849 | G30: =G28+G29 -> -4247.5 | H30: =H28+H29 -> -2643.377 | I30: =I28+I29 -> -1528.945 | J30: =J28+J29 -> 1398.456 | ... N30: =N28+N29 -> 10944.756 | O30: =SUM(C30:N30) -> -6100.141
B32: Накопленная чистая прибыль | C32: =C30 -> -11510.976 | D32: =C32+D30 -> -18348.976 | E32: =D32+E30 -> -24678.701 | F32: =E32+F30 -> -30125.55 | G32: =F32+G30 -> -34373.05 | H32: =G32+H30 -> -37016.427 | I32: =H32+I30 -> -38545.372 | J32: =I32+J30 -> -37146.916 | K32: =J32+K30 -> -34022.974 | ... N32: =M32+N30 -> -6100.141 | O32: =N32 -> -6100.141

Sheet P&L ERA
B2: P&L · ERA (€, 12 месяцев)
B3: Статья P&L | C3: Янв | D3: Фев | E3: Мар | F3: Апр | G3: Май | H3: Июн | I3: Июл | J3: Авг | K3: Сен | L3: Окт | M3: Ноя | N3: Дек | O3: ГОД
B4: Объём продаж, ед | C4: =SUM(Допущения!C$25:C$29) -> 129.1 | D4: =SUM(Допущения!D$25:D$29) -> 286.5 | E4: =SUM(Допущения!E$25:E$29) -> 512.8 | F4: =SUM(Допущения!F$25:F$29) -> 779.1 | G4: =SUM(Допущения!G$25:G$29) -> 1075.5 | H4: =SUM(Допущения!H$25:H$29) -> 1424.4 | I4: =SUM(Допущения!I$25:I$29) -> 1742.3 | J4: =SUM(Допущения!J$25:J$29) -> 2228.5 | ... N4: =SUM(Допущения!N$25:N$29) -> 4118.4 | O4: =SUM(C4:N4) -> 21831.1
B6: Валовая выручка | C6: =SUMPRODUCT(Допущения!C$25:C$29,Допущения!$C$18:$C$22) -> 3043.2 | D6: =SUMPRODUCT(Допущения!D$25:D$29,Допущения!$C$18:$C$22) -> 6730.2 | E6: =SUMPRODUCT(Допущения!E$25:E$29,Допущения!$C$18:$C$22) -> 12021.9 | F6: =SUMPRODUCT(Допущения!F$25:F$29,Допущения!$C$18:$C$22) -> 18182.7 | G6: =SUMPRODUCT(Допущения!G$25:G$29,Допущения!$C$18:$C$22) -> 25101 | H6: =SUMPRODUCT(Допущения!H$25:H$29,Допущения!$C$18:$C$22) -> 33242.1 | I6: =SUMPRODUCT(Допущения!I$25:I$29,Допущения!$C$18:$C$22) -> 40730.1 | J6: =SUMPRODUCT(Допущения!J$25:J$29,Допущения!$C$18:$C$22) -> 52143.6 | ... N6: =SUMPRODUCT(Допущения!N$25:N$29,Допущения!$C$18:$C$22) -> 96573.6 | O6: =SUM(C6:N6) -> 511267.5
B7: Возвраты (% от выручки) | C7: =-C6*Допущения!$C$11 -> -30.432 | D7: =-D6*Допущения!$C$11 -> -67.302 | E7: =-E6*Допущения!$C$11 -> -120.219 | F7: =-F6*Допущения!$C$11 -> -181.827 | G7: =-G6*Допущения!$C$11 -> -251.01 | H7: =-H6*Допущения!$C$11 -> -332.421 | I7: =-I6*Допущения!$C$11 -> -407.301 | J7: =-J6*Допущения!$C$11 -> -521.436 | ... N7: =-N6*Допущения!$C$11 -> -965.736 | O7: =SUM(C7:N7) -> -5112.675
B8: Чистая выручка | C8: =C6+C7 -> 3012.768 | D8: =D6+D7 -> 6662.898 | E8: =E6+E7 -> 11901.681 | F8: =F6+F7 -> 18000.873 | G8: =G6+G7 -> 24849.99 | H8: =H6+H7 -> 32909.679 | I8: =I6+I7 -> 40322.799 | J8: =J6+J7 -> 51622.164 | ... N8: =N6+N7 -> 95607.864 | O8: =SUM(C8:N8) -> 506154.83
B10: Себестоимость товара (COGS) | C10: =-SUMPRODUCT(Допущения!C$25:C$29,Допущения!$F$18:$F$22) -> -560.247 | D10: =-SUMPRODUCT(Допущения!D$25:D$29,Допущения!$F$18:$F$22) -> -1204.609 | E10: =-SUMPRODUCT(Допущения!E$25:E$29,Допущения!$F$18:$F$22) -> -2119.016 | F10: =-SUMPRODUCT(Допущения!F$25:F$29,Допущения!$F$18:$F$22) -> -3145.376 | G10: =-SUMPRODUCT(Допущения!G$25:G$29,Допущения!$F$18:$F$22) -> -4325.22 | H10: =-SUMPRODUCT(Допущения!H$25:H$29,Допущения!$F$18:$F$22) -> -5710.737 | I10: =-SUMPRODUCT(Допущения!I$25:I$29,Допущения!$F$18:$F$22) -> -7018.669 | J10: =-SUMPRODUCT(Допущения!J$25:J$29,Допущения!$F$18:$F$22) -> -8996.085 | ... N10: =-SUMPRODUCT(Допущения!N$25:N$29,Допущения!$F$18:$F$22) -> -16711.488 | O10: =SUM(C10:N10) -> -88480.235
B11: ВАЛОВАЯ ПРИБЫЛЬ | C11: =C8+C10 -> 2452.521 | D11: =D8+D10 -> 5458.289 | E11: =E8+E10 -> 9782.665 | F11: =F8+F10 -> 14855.497 | G11: =G8+G10 -> 20524.77 | H11: =H8+H10 -> 27198.942 | I11: =I8+I10 -> 33304.13 | J11: =J8+J10 -> 42626.079 | ... N11: =N8+N10 -> 78896.376 | O11: =SUM(C11:N11) -> 417674.59
B12: % валовой прибыли | C12: =IF(C6=0,0,C11/C6) -> 0.80590201 | D12: =IF(D6=0,0,D11/D6) -> 0.81101438 | E12: =IF(E6=0,0,E11/E6) -> 0.81373701 | F12: =IF(F6=0,0,F11/F6) -> 0.81701271 | G12: =IF(G6=0,0,G11/G6) -> 0.81768734 | H12: =IF(H6=0,0,H11/H6) -> 0.81820769 | I12: =IF(I6=0,0,I11/I6) -> 0.81767857 | J12: =IF(J6=0,0,J11/J6) -> 0.8174748 | ... O12: =IF(O6=0,0,O11/O6) -> 0.81693945
B15: Комиссия Amazon (15%) | C15: =-C6*Допущения!$C$6 -> -456.48 | D15: =-D6*Допущения!$C$6 -> -1009.53 | E15: =-E6*Допущения!$C$6 -> -1803.285 | F15: =-F6*Допущения!$C$6 -> -2727.405 | G15: =-G6*Допущения!$C$6 -> -3765.15 | H15: =-H6*Допущения!$C$6 -> -4986.315 | I15: =-I6*Допущения!$C$6 -> -6109.515 | J15: =-J6*Допущения!$C$6 -> -7821.54 | ... N15: =-N6*Допущения!$C$6 -> -14486.04 | O15: =SUM(C15:N15) -> -76690.125
B16: FBA фулфилмент | C16: =-SUMPRODUCT(Допущения!C$25:C$29,Допущения!$D$18:$D$22) -> -387.3 | D16: =-SUMPRODUCT(Допущения!D$25:D$29,Допущения!$D$18:$D$22) -> -859.5 | E16: =-SUMPRODUCT(Допущения!E$25:E$29,Допущения!$D$18:$D$22) -> -1538.4 | F16: =-SUMPRODUCT(Допущения!F$25:F$29,Допущения!$D$18:$D$22) -> -2337.3 | G16: =-SUMPRODUCT(Допущения!G$25:G$29,Допущения!$D$18:$D$22) -> -3226.5 | H16: =-SUMPRODUCT(Допущения!H$25:H$29,Допущения!$D$18:$D$22) -> -4273.2 | I16: =-SUMPRODUCT(Допущения!I$25:I$29,Допущения!$D$18:$D$22) -> -5226.9 | J16: =-SUMPRODUCT(Допущения!J$25:J$29,Допущения!$D$18:$D$22) -> -6685.5 | ... N16: =-SUMPRODUCT(Допущения!N$25:N$29,Допущения!$D$18:$D$22) -> -12355.2 | O16: =SUM(C16:N16) -> -65493.3
B17: Входящая логистика (завод→FBA) | C17: =-SUM(Допущения!C$25:C$29)*Допущения!$C$8 -> -32.275 | D17: =-SUM(Допущения!D$25:D$29)*Допущения!$C$8 -> -71.625 | E17: =-SUM(Допущения!E$25:E$29)*Допущения!$C$8 -> -128.2 | F17: =-SUM(Допущения!F$25:F$29)*Допущения!$C$8 -> -194.775 | G17: =-SUM(Допущения!G$25:G$29)*Допущения!$C$8 -> -268.875 | H17: =-SUM(Допущения!H$25:H$29)*Допущения!$C$8 -> -356.1 | I17: =-SUM(Допущения!I$25:I$29)*Допущения!$C$8 -> -435.575 | J17: =-SUM(Допущения!J$25:J$29)*Допущения!$C$8 -> -557.125 | ... N17: =-SUM(Допущения!N$25:N$29)*Допущения!$C$8 -> -1029.6 | O17: =SUM(C17:N17) -> -5457.775
B18: Преп и маркировка | C18: =-SUM(Допущения!C$25:C$29)*Допущения!$C$9 -> -51.64 | D18: =-SUM(Допущения!D$25:D$29)*Допущения!$C$9 -> -114.6 | E18: =-SUM(Допущения!E$25:E$29)*Допущения!$C$9 -> -205.12 | F18: =-SUM(Допущения!F$25:F$29)*Допущения!$C$9 -> -311.64 | G18: =-SUM(Допущения!G$25:G$29)*Допущения!$C$9 -> -430.2 | H18: =-SUM(Допущения!H$25:H$29)*Допущения!$C$9 -> -569.76 | I18: =-SUM(Допущения!I$25:I$29)*Допущения!$C$9 -> -696.92 | J18: =-SUM(Допущения!J$25:J$29)*Допущения!$C$9 -> -891.4 | ... N18: =-SUM(Допущения!N$25:N$29)*Допущения!$C$9 -> -1647.36 | O18: =SUM(C18:N18) -> -8732.44
B19: Хранение Amazon | C19: =-SUM(Допущения!C$25:C$29)*Допущения!$C$10 -> -19.365 | D19: =-SUM(Допущения!D$25:D$29)*Допущения!$C$10 -> -42.975 | E19: =-SUM(Допущения!E$25:E$29)*Допущения!$C$10 -> -76.92 | F19: =-SUM(Допущения!F$25:F$29)*Допущения!$C$10 -> -116.865 | G19: =-SUM(Допущения!G$25:G$29)*Допущения!$C$10 -> -161.325 | H19: =-SUM(Допущения!H$25:H$29)*Допущения!$C$10 -> -213.66 | I19: =-SUM(Допущения!I$25:I$29)*Допущения!$C$10 -> -261.345 | J19: =-SUM(Допущения!J$25:J$29)*Допущения!$C$10 -> -334.275 | ... N19: =-SUM(Допущения!N$25:N$29)*Допущения!$C$10 -> -617.76 | O19: =SUM(C19:N19) -> -3274.665
B20: Обработка возвратов | C20: =-SUM(Допущения!C$25:C$29)*Допущения!$C$11*Допущения!$C$12 -> -1.291 | D20: =-SUM(Допущения!D$25:D$29)*Допущения!$C$11*Допущения!$C$12 -> -2.865 | E20: =-SUM(Допущения!E$25:E$29)*Допущения!$C$11*Допущения!$C$12 -> -5.128 | F20: =-SUM(Допущения!F$25:F$29)*Допущения!$C$11*Допущения!$C$12 -> -7.791 | G20: =-SUM(Допущения!G$25:G$29)*Допущения!$C$11*Допущения!$C$12 -> -10.755 | H20: =-SUM(Допущения!H$25:H$29)*Допущения!$C$11*Допущения!$C$12 -> -14.244 | I20: =-SUM(Допущения!I$25:I$29)*Допущения!$C$11*Допущения!$C$12 -> -17.423 | J20: =-SUM(Допущения!J$25:J$29)*Допущения!$C$11*Допущения!$C$12 -> -22.285 | ... N20: =-SUM(Допущения!N$25:N$29)*Допущения!$C$11*Допущения!$C$12 -> -41.184 | O20: =SUM(C20:N20) -> -218.311
B21: Купоны / промо | C21: =-SUM(Допущения!C$41:C$45) -> -75.9 | D21: =-SUM(Допущения!D$41:D$45) -> -183.61 | E21: =-SUM(Допущения!E$41:E$45) -> -335.96 | F21: =-SUM(Допущения!F$41:F$45) -> -532.96 | G21: =-SUM(Допущения!G$41:G$45) -> -805.63 | H21: =-SUM(Допущения!H$41:H$45) -> -1025.15 | I21: =-SUM(Допущения!I$41:I$45) -> -1209.23 | J21: =-SUM(Допущения!J$41:J$45) -> -1492.22 | ... N21: =-SUM(Допущения!N$41:N$45) -> -2416.74 | O21: =SUM(C21:N21) -> -14027.14
B22: Реклама PPC | C22: =-SUM(Допущения!C$33:C$37) -> -6363 | D22: =-SUM(Допущения!D$33:D$37) -> -7560 | E22: =-SUM(Допущения!E$33:E$37) -> -9602 | F22: =-SUM(Допущения!F$33:F$37) -> -11690 | G22: =-SUM(Допущения!G$33:G$37) -> -13763 | H22: =-SUM(Допущения!H$33:H$37) -> -16113 | I22: =-SUM(Допущения!I$33:I$37) -> -18637 | J22: =-SUM(Допущения!J$33:J$37) -> -21260 | ... N22: =-SUM(Допущения!N$33:N$37) -> -33494 | O22: =SUM(C22:N22) -> -219125
B24: МАРЖИНАЛЬНАЯ ПРИБЫЛЬ | C24: =C8+C10+C15+C16+C17+C18+C19+C20+C21+C22 -> -4934.73 | D24: =D8+D10+D15+D16+D17+D18+D19+D20+D21+D22 -> -4386.416 | E24: =E8+E10+E15+E16+E17+E18+E19+E20+E21+E22 -> -3912.348 | F24: =F8+F10+F15+F16+F17+F18+F19+F20+F21+F22 -> -3063.239 | G24: =G8+G10+G15+G16+G17+G18+G19+G20+G21+G22 -> -1906.665 | H24: =H8+H10+H15+H16+H17+H18+H19+H20+H21+H22 -> -352.487 | I24: =I8+I10+I15+I16+I17+I18+I19+I20+I21+I22 -> 710.222 | J24: =J8+J10+J15+J16+J17+J18+J19+J20+J21+J22 -> 3561.734 | ... N24: =N8+N10+N15+N16+N17+N18+N19+N20+N21+N22 -> 12808.492 | O24: =SUM(C24:N24) -> 24655.834
B25: % маржи (от выручки) | C25: =IF(C6=0,0,C24/C6) -> -1.6215595 | D25: =IF(D6=0,0,D24/D6) -> -0.65175121 | E25: =IF(E6=0,0,E24/E6) -> -0.32543508 | F25: =IF(F6=0,0,F24/F6) -> -0.16846997 | G25: =IF(G6=0,0,G24/G6) -> -0.075959723 | H25: =IF(H6=0,0,H24/H6) -> -0.010603632 | I25: =IF(I6=0,0,I24/I6) -> 0.017437276 | J25: =IF(J6=0,0,J24/J6) -> 0.068306254 | ... O25: =IF(O6=0,0,O24/O6) -> 0.048224919
B27: Постоянные расходы (опер.) | C27: =-Допущения!$C$13 -> -2500 | D27: =-Допущения!$C$13 -> -2500 | E27: =-Допущения!$C$13 -> -2500 | F27: =-Допущения!$C$13 -> -2500 | G27: =-Допущения!$C$13 -> -2500 | H27: =-Допущения!$C$13 -> -2500 | I27: =-Допущения!$C$13 -> -2500 | J27: =-Допущения!$C$13 -> -2500 | ... N27: =-Допущения!$C$13 -> -2500 | O27: =SUM(C27:N27) -> -30000
B28: EBITDA | C28: =C24+C27 -> -7434.73 | D28: =D24+D27 -> -6886.416 | E28: =E24+E27 -> -6412.348 | F28: =F24+F27 -> -5563.239 | G28: =G24+G27 -> -4406.665 | H28: =H24+H27 -> -2852.487 | I28: =I24+I27 -> -1789.778 | J28: =J24+J27 -> 1061.734 | ... N28: =N24+N27 -> 10308.492 | O28: =SUM(C28:N28) -> -5344.166
B29: Разовые расходы (старт) | C29: =-Допущения!$C$15 -> -4100 | D29: 0 | E29: 0 | F29: 0 | G29: 0 | H29: 0 | I29: 0 | J29: 0 | K29: 0 | L29: 0 | M29: 0 | N29: 0 | O29: =SUM(C29:N29) -> -4100
B30: ЧИСТАЯ ПРИБЫЛЬ | C30: =C28+C29 -> -11534.73 | D30: =D28+D29 -> -6886.416 | E30: =E28+E29 -> -6412.348 | F30: =F28+F29 -> -5563.239 | G30: =G28+G29 -> -4406.665 | H30: =H28+H29 -> -2852.487 | I30: =I28+I29 -> -1789.778 | J30: =J28+J29 -> 1061.734 | ... N30: =N28+N29 -> 10308.492 | O30: =SUM(C30:N30) -> -9444.166
B32: Накопленная чистая прибыль | C32: =C30 -> -11534.73 | D32: =C32+D30 -> -18421.146 | E32: =D32+E30 -> -24833.494 | F32: =E32+F30 -> -30396.733 | G32: =F32+G30 -> -34803.398 | H32: =G32+H30 -> -37655.885 | I32: =H32+I30 -> -39445.663 | J32: =I32+J30 -> -38383.929 | K32: =J32+K30 -> -35663.248 | ... N32: =M32+N30 -> -9444.166 | O32: =N32 -> -9444.166

Sheet Юнит-экономика
B2: ЮНИТ-ЭКОНОМИКА ПО ПРОДУКТАМ (€)
B3: Вклад каждого продукта в годовой результат. Формулы тянут объёмы, цены и затраты с листа «Допущения».
B5: НА ЕДИНИЦУ ТОВАРА | C5: Inositol | D5: Magnesium B6 | E5: Probiotic | F5: Pet Probiotic | G5: Retinol Cream
B6: Цена продажи | C6: =Допущения!$C$18 -> 25 | D6: =Допущения!$C$19 -> 19 | E6: =Допущения!$C$20 -> 21 | F6: =Допущения!$C$21 -> 30 | G6: =Допущения!$C$22 -> 23
B7: Себестоимость — Меривуд | C7: =-Допущения!$E$18 -> -4.86 | D7: =-Допущения!$E$19 -> -4.9 | E7: =-Допущения!$E$20 -> -3.1 | F7: =-Допущения!$E$21 -> -3.49 | G7: =-Допущения!$E$22 -> -3.5
B8: Себестоимость — ERA | C8: =-Допущения!$F$18 -> -5.16 | D8: =-Допущения!$F$19 -> -4.79 | E8: =-Допущения!$F$20 -> -3.74 | F8: =-Допущения!$F$21 -> -3.49 | G8: =-Допущения!$F$22 -> -3.5
B9: Комиссия Amazon (15%) | C9: =-Допущения!$C$18*Допущения!$C$6 -> -3.75 | D9: =-Допущения!$C$19*Допущения!$C$6 -> -2.85 | E9: =-Допущения!$C$20*Допущения!$C$6 -> -3.15 | F9: =-Допущения!$C$21*Допущения!$C$6 -> -4.5 | G9: =-Допущения!$C$22*Допущения!$C$6 -> -3.45
B10: FBA фулфилмент | C10: =-Допущения!$D$18 -> -3 | D10: =-Допущения!$D$19 -> -3 | E10: =-Допущения!$D$20 -> -3 | F10: =-Допущения!$D$21 -> -3 | G10: =-Допущения!$D$22 -> -3
B11: Логистика+преп+хранение | C11: =-(Допущения!$C$8+Допущения!$C$9+Допущения!$C$10) -> -0.8 | D11: =-(Допущения!$C$8+Допущения!$C$9+Допущения!$C$10) -> -0.8 | E11: =-(Допущения!$C$8+Допущения!$C$9+Допущения!$C$10) -> -0.8 | F11: =-(Допущения!$C$8+Допущения!$C$9+Допущения!$C$10) -> -0.8 | G11: =-(Допущения!$C$8+Допущения!$C$9+Допущения!$C$10) -> -0.8
B12: Купон (средн. на ед.) | C12: =-Допущения!O$41/Допущения!O$25 -> -0.60860643 | D12: =-Допущения!O$42/Допущения!O$26 -> -0.5315954 | E12: =-Допущения!O$43/Допущения!O$27 -> -0.58677844 | F12: =-Допущения!O$44/Допущения!O$28 -> -0.83669365 | G12: =-Допущения!O$45/Допущения!O$29 -> -0.64325914
B13: Маржа на ед. — Меривуд (до PPC) | C13: =C6+C7+C9+C10+C11+C12 -> 11.981394 | D13: =D6+D7+D9+D10+D11+D12 -> 6.9184046 | E13: =E6+E7+E9+E10+E11+E12 -> 10.363222 | F13: =F6+F7+F9+F10+F11+F12 -> 17.373306 | G13: =G6+G7+G9+G10+G11+G12 -> 11.606741
B14: Маржа на ед. — ERA (до PPC) | C14: =C6+C8+C9+C10+C11+C12 -> 11.681394 | D14: =D6+D8+D9+D10+D11+D12 -> 7.0284046 | E14: =E6+E8+E9+E10+E11+E12 -> 9.7232216 | F14: =F6+F8+F9+F10+F11+F12 -> 17.373306 | G14: =G6+G8+G9+G10+G11+G12 -> 11.606741
B16: ГОДОВОЙ ВКЛАД (€/год) | C16: Inositol | D16: Magnesium B6 | E16: Probiotic | F16: Pet Probiotic | G16: Retinol Cream | I16: ИТОГО
B17: Объём продаж, ед | C17: =Допущения!O$25 -> 2865.3 | D17: =Допущения!O$26 -> 4829.5 | E17: =Допущения!O$27 -> 4712 | F17: =Допущения!O$28 -> 4594.8 | G17: =Допущения!O$29 -> 4829.5 | I17: =SUM(C17:G17) -> 21831.1
B18: Валовая выручка | C18: =Допущения!O$25*Допущения!$C$18 -> 71632.5 | D18: =Допущения!O$26*Допущения!$C$19 -> 91760.5 | E18: =Допущения!O$27*Допущения!$C$20 -> 98952 | F18: =Допущения!O$28*Допущения!$C$21 -> 137844 | G18: =Допущения!O$29*Допущения!$C$22 -> 111078.5 | I18: =SUM(C18:G18) -> 511267.5
B19: Себест. (Меривуд) | C19: =-Допущения!O$25*Допущения!$E$18 -> -13925.358 | D19: =-Допущения!O$26*Допущения!$E$19 -> -23664.55 | E19: =-Допущения!O$27*Допущения!$E$20 -> -14607.2 | F19: =-Допущения!O$28*Допущения!$E$21 -> -16035.852 | G19: =-Допущения!O$29*Допущения!$E$22 -> -16903.25 | I19: =SUM(C19:G19) -> -85136.21
B20: Комиссия+FBA+лог. | C20: =-Допущения!O$25*(Допущения!$C$18*Допущения!$C$6+Допущения!$D$18+Допущения!$C$8+Допущения!$C$9+Допущения!$C$10) -> -21633.015 | D20: =-Допущения!O$26*(Допущения!$C$19*Допущения!$C$6+Допущения!$D$19+Допущения!$C$8+Допущения!$C$9+Допущения!$C$10) -> -32116.175 | E20: =-Допущения!O$27*(Допущения!$C$20*Допущения!$C$6+Допущения!$D$20+Допущения!$C$8+Допущения!$C$9+Допущения!$C$10) -> -32748.4 | F20: =-Допущения!O$28*(Допущения!$C$21*Допущения!$C$6+Допущения!$D$21+Допущения!$C$8+Допущения!$C$9+Допущения!$C$10) -> -38136.84 | G20: =-Допущения!O$29*(Допущения!$C$22*Допущения!$C$6+Допущения!$D$22+Допущения!$C$8+Допущения!$C$9+Допущения!$C$10) -> -35013.875 | I20: =SUM(C20:G20) -> -159648.3
B21: Купоны | C21: =-Допущения!O$41 -> -1743.84 | D21: =-Допущения!O$42 -> -2567.34 | E21: =-Допущения!O$43 -> -2764.9 | F21: =-Допущения!O$44 -> -3844.44 | G21: =-Допущения!O$45 -> -3106.62 | I21: =SUM(C21:G21) -> -14027.14
B22: Реклама PPC | C22: =-Допущения!O$33 -> -51454 | D22: =-Допущения!O$34 -> -40568 | E22: =-Допущения!O$35 -> -47030 | F22: =-Допущения!O$36 -> -51565 | G22: =-Допущения!O$37 -> -28508 | I22: =SUM(C22:G22) -> -219125
B23: ВКЛАД после PPC — Меривуд | C23: =C18+C19+C20+C21+C22 -> -17123.713 | D23: =D18+D19+D20+D21+D22 -> -7155.565 | E23: =E18+E19+E20+E21+E22 -> 1801.5 | F23: =F18+F19+F20+F21+F22 -> 28261.868 | G23: =G18+G19+G20+G21+G22 -> 27546.755 | I23: =SUM(C23:G23) -> 33330.845
B24: ВКЛАД после PPC — ERA | C24: =C18-Допущения!O$25*Допущения!$F$18+C20+C21+C22 -> -17983.303 | D24: =D18-Допущения!O$26*Допущения!$F$19+D20+D21+D22 -> -6624.32 | E24: =E18-Допущения!O$27*Допущения!$F$20+E20+E21+E22 -> -1214.18 | F24: =F18-Допущения!O$28*Допущения!$F$21+F20+F21+F22 -> 28261.868 | G24: =G18-Допущения!O$29*Допущения!$F$22+G20+G21+G22 -> 27546.755 | I24: =SUM(C24:G24) -> 29986.82
B26: Примечание: «вклад после PPC» — это маржа продукта до постоянных расходов (команда, софт, юр.) и разовых затрат старта. Сумма по всем продуктам минус эти расходы = операционный результат.

Sheet Заводы
B2: СРАВНЕНИЕ ПРОИЗВОДИТЕЛЕЙ
B3: Условия из исходного файла (лист «Заводы + Юнит эк.»). Выделены два производителя из задания.
B5: Параметр | C5: МЕРИВУД (Merywood) | D5: ERAscientifico | E5: Альтернативы (справочно)
B6: Локация | C6: Эстония | D6: Латвия | E6: MillMax — Латвия; Nutriliq — Бельгия
B7: Сайт | C7: — | D7: erascientifico.com | E7: nutriliq.eu / millmax
B8: Мин. партия (MOQ), шт | C8: 5 000 | D8: 1 000 | E8: MillMax 1000-3000; Nutriliq 890
B9: НДС (intra-EU B2B → reverse charge) | C9: 24% | D9: 21–22% | E9: MillMax 22%; Nutriliq 21%
B10: Условия оплаты | C10: 100% предоплата | D10: 60% предоплата | E10: Nutriliq 50% + отсрочка 30 дн
B11: Доставка до Amazon | C11: Да | D11: Да | E11: Да (все)
B12: Хранение | C12: 2 недели | D12: 2 недели | E12: Nutriliq — нет
B13: Регистрация этикетки «под ключ» | C13: Да | D13: Да | E13: MillMax — нет
B14: Срок производства (lead time) | C14: 6–8 недель | D14: 8–9 нед (затем 6–8) | E14: —
B15: Наличие сырья | C15: Под заказ | D15: В наличии | E15: Nutriliq/MillMax — под заказ
B16: Полнота ассортимента | C16: Весь, кроме Pet-пробиотика | D16: Весь, кроме Ретинола | E16: MillMax — нет пребиотика
... B19: Особенности | C19: Регистрирует этикетки под ключ, широкий ассортимент | D19: Сырьё в наличии, быстрый старт, этикетки под ключ | E19: MillMax — возможны вопросы к качеству
B21: ВАЖНО — перекрёстный сорсинг (cross-sourcing)
B22: Ни один из двух производителей не закрывает все 5 SKU. МЕРИВУД не делает пробиотик для животных (Pet); ERA не делает Ретинол. Поэтому в каждом сценарии один товар берётся у второго производителя: • Сценарий «МЕРИВУД»: 4 товара — Меривуд, Pet-пробиотик — у ERA (€3,49/ед). • Сценарий «ERA»: 4 товара — ERA, Ретинол — у Меривуд (€3,50/ед). Все прочие условия (объёмы, цены продажи, PPC, купоны, комиссии Amazon) одинаковы — поэтому разница в P&L определяется ТОЛЬКО себестоимостью товара.

Sheet Допущения
B2: ДОПУЩЕНИЯ И ВХОДНЫЕ ДАННЫЕ
B3: Синие ячейки — редактируемые параметры. Меняйте их, и P&L пересчитается.
B5: ГЛОБАЛЬНЫЕ ПАРАМЕТРЫ | C5: Значение
B6: Комиссия Amazon (referral, % от выручки) | C6: 0.15
B7: FBA фулфилмент по умолчанию (€/ед) | C7: 3
B8: Входящая логистика завод→Amazon (€/ед) | C8: 0.25
B9: Преп и маркировка / FNSKU (€/ед) | C9: 0.4
B10: Хранение Amazon (€/ед, аллокация) | C10: 0.15
B11: Процент возвратов | C11: 0.01
B12: Обработка возврата (€/ед возврата) | C12: 1
B13: Постоянные расходы (€/мес: команда+софт+юр) | C13: 2500
B14: НДС с продаж — справочно, DE (не вычитается в базе) | C14: 0.19
B15: Разовые расходы старта (бренд, дизайн, листинги), € | C15: 4100
B17: ПАРАМЕТРЫ ПО ПРОДУКТАМ | C17: Цена € | D17: FBA €/ед | E17: COGS Меривуд € | F17: COGS ERA € | G17: Источник МВ | H17: Источник ERA
B18: Inositol (Иноситол) | C18: 25 | D18: 3 | E18: 4.86 | F18: 5.16 | G18: Меривуд | H18: ERA
B19: Magnesium B6 (Магний) | C19: 19 | D19: 3 | E19: 4.9 | F19: 4.79 | G19: Меривуд | H19: ERA
B20: Probiotic — люди (Probioful) | C20: 21 | D20: 3 | E20: 3.1 | F20: 3.74 | G20: Меривуд | H20: ERA
B21: Pet Probiotic — животные (Pet) | C21: 30 | D21: 3 | E21: 3.49 | F21: 3.49 | G21: ERA (кросс) | H21: ERA
B22: Retinol Cream (Ретинол) | C22: 23 | D22: 3 | E22: 3.5 | F22: 3.5 | G22: Меривуд | H22: Меривуд (кросс)
B24: ОБЪЁМ ПРОДАЖ ПО МЕСЯЦАМ (ед) — план запуска | C24: Янв | D24: Фев | E24: Мар | F24: Апр | G24: Май | H24: Июн | I24: Июл | J24: Авг | K24: Сен | L24: Окт | M24: Ноя | N24: Дек | O24: Год
B25: Inositol (Иноситол) | C25: 44.1 | D25: 69.3 | E25: 96.6 | F25: 90 | G25: 112.5 | H25: 136.5 | I25: 194.4 | J25: 264.6 | K25: 348 | L25: 445.5 | M25: 502.2 | N25: 561.6 | O25: =SUM(C25:N25) -> 2865.3
B26: Magnesium B6 (Магний) | C26: 23.6 | D26: 57.8 | E26: 108.7 | F26: 178.2 | G26: 247.5 | H26: 329.6 | I26: 394.9 | J26: 499.8 | K26: 578.5 | L26: 708.8 | M26: 802.1 | N26: 900 | O26: =SUM(C26:N26) -> 4829.5
B27: Probiotic — люди (Probioful) | C27: 20.5 | D27: 53.1 | E27: 102.5 | F27: 170.3 | G27: 238.5 | H27: 319.4 | I27: 384.3 | J27: 488 | K27: 566.4 | L27: 695.2 | M27: 788.2 | N27: 885.6 | O27: =SUM(C27:N27) -> 4712
B28: Pet Probiotic — животные (Pet) | C28: 17.3 | D28: 48.5 | E28: 96.3 | F28: 162.4 | G28: 229.5 | H28: 309.3 | I28: 373.8 | J28: 476.3 | K28: 554.2 | L28: 681.8 | M28: 774.2 | N28: 871.2 | O28: =SUM(C28:N28) -> 4594.8
B29: Retinol Cream (Ретинол) | C29: 23.6 | D29: 57.8 | E29: 108.7 | F29: 178.2 | G29: 247.5 | H29: 329.6 | I29: 394.9 | J29: 499.8 | K29: 578.5 | L29: 708.8 | M29: 802.1 | N29: 900 | O29: =SUM(C29:N29) -> 4829.5
B30: Итого, ед | C30: =SUM(C25:C29) -> 129.1 | D30: =SUM(D25:D29) -> 286.5 | E30: =SUM(E25:E29) -> 512.8 | F30: =SUM(F25:F29) -> 779.1 | G30: =SUM(G25:G29) -> 1075.5 | H30: =SUM(H25:H29) -> 1424.4 | I30: =SUM(I25:I29) -> 1742.3 | J30: =SUM(J25:J29) -> 2228.5 | ... O30: =SUM(O25:O29) -> 21831.1
B32: РЕКЛАМА PPC ПО МЕСЯЦАМ (€) | C32: Янв | D32: Фев | E32: Мар | F32: Апр | G32: Май | H32: Июн | I32: Июл | J32: Авг | K32: Сен | L32: Окт | M32: Ноя | N32: Дек | O32: Год
B33: Inositol (Иноситол) | C33: 3000 | D33: 3000 | E33: 3000 | F33: 3000 | G33: 3000 | H33: 3256 | I33: 3744 | J33: 4240 | K33: 5040 | L33: 5578 | M33: 6444 | N33: 8152 | O33: =SUM(C33:N33) -> 51454
B34: Magnesium B6 (Магний) | C34: 893 | D34: 1165 | E34: 1647 | F34: 2138 | G34: 2626 | H34: 3118 | I34: 3598 | J34: 4097 | K34: 4579 | L34: 5085 | M34: 5569 | N34: 6053 | O34: =SUM(C34:N34) -> 40568
B35: Probiotic — люди (Probioful) | C35: 919 | D35: 1283 | E35: 1857 | F35: 2442 | G35: 3023 | H35: 3609 | I35: 4182 | J35: 4775 | K35: 5351 | L35: 5952 | M35: 6530 | N35: 7107 | O35: =SUM(C35:N35) -> 47030
B36: Pet Probiotic — животные (Pet) | C36: 880 | D36: 1313 | E36: 1961 | F36: 2623 | G36: 3281 | H36: 3946 | I36: 4593 | J36: 5269 | K36: 5919 | L36: 6606 | M36: 7260 | N36: 7914 | O36: =SUM(C36:N36) -> 51565
B37: Retinol Cream (Ретинол) | C37: 671 | D37: 799 | E37: 1137 | F37: 1487 | G37: 1833 | H37: 2184 | I37: 2520 | J37: 2879 | K37: 3218 | L37: 3585 | M37: 3927 | N37: 4268 | O37: =SUM(C37:N37) -> 28508
B38: Итого PPC, € | C38: =SUM(C33:C37) -> 6363 | D38: =SUM(D33:D37) -> 7560 | E38: =SUM(E33:E37) -> 9602 | F38: =SUM(F33:F37) -> 11690 | G38: =SUM(G33:G37) -> 13763 | H38: =SUM(H33:H37) -> 16113 | I38: =SUM(I33:I37) -> 18637 | J38: =SUM(J33:J37) -> 21260 | ... O38: =SUM(O33:O37) -> 219125
B40: КУПОНЫ / ПРОМО ПО МЕСЯЦАМ (€) | C40: Янв | D40: Фев | E40: Мар | F40: Апр | G40: Май | H40: Июн | I40: Июл | J40: Авг | K40: Сен | L40: Окт | M40: Ноя | N40: Дек | O40: Год
B41: Inositol (Иноситол) | C41: 0 | D41: 0 | E41: 0 | F41: 0 | G41: 90.48 | H41: 105.48 | I41: 144.48 | J41: 189.48 | K41: 240.48 | L41: 297.48 | M41: 324.48 | N41: 351.48 | O41: =SUM(C41:N41) -> 1743.84
B42: Magnesium B6 (Магний) | C42: 17.58 | D42: 40.38 | E42: 72.3 | F42: 113.34 | G42: 150.96 | H42: 193.14 | I42: 222.78 | J42: 271.8 | K42: 303.72 | L42: 359.58 | M42: 393.78 | N42: 427.98 | O42: =SUM(C42:N42) -> 2567.34
B43: Probiotic — люди (Probioful) | C43: 16.86 | D43: 41.05 | E43: 75.32 | F43: 119.68 | G43: 160.75 | H43: 206.87 | I43: 239.63 | J43: 293.3 | K43: 328.58 | L43: 389.82 | M43: 427.62 | N43: 465.42 | O43: =SUM(C43:N43) -> 2764.9
B44: Pet Probiotic — животные (Pet) | C44: 20.28 | D44: 53.4 | E44: 100.92 | F44: 162.84 | G44: 220.8 | H44: 285.96 | I44: 332.76 | J44: 408.72 | K44: 459.12 | L44: 545.88 | M44: 599.88 | N44: 653.88 | O44: =SUM(C44:N44) -> 3844.44
B45: Retinol Cream (Ретинол) | C45: 21.18 | D45: 48.78 | E45: 87.42 | F45: 137.1 | G45: 182.64 | H45: 233.7 | I45: 269.58 | J45: 328.92 | K45: 367.56 | L45: 435.18 | M45: 476.58 | N45: 517.98 | O45: =SUM(C45:N45) -> 3106.62
B46: Итого купоны, € | C46: =SUM(C41:C45) -> 75.9 | D46: =SUM(D41:D45) -> 183.61 | E46: =SUM(E41:E45) -> 335.96 | F46: =SUM(F41:F45) -> 532.96 | G46: =SUM(G41:G45) -> 805.63 | H46: =SUM(H41:H45) -> 1025.15 | I46: =SUM(I41:I45) -> 1209.23 | J46: =SUM(J41:J45) -> 1492.22 | ... O46: =SUM(O41:O45) -> 14027.14
